{
    "name": "testimonials-marquee",
    "type": "registry:block",
    "dependencies": [
        "framer-motion",
        "lucide-react"
    ],
    "registryDependencies": [],
    "files": [
        {
            "path": "registry/testimonials-marquee/testimonials-marquee.tsx",
            "content": "\"use client\";\r\n\r\nimport React from \"react\";\r\nimport { motion } from \"framer-motion\";\r\nimport { Star, Quote } from \"lucide-react\";\r\n\r\nconst testimonials = [\r\n  {\r\n    name: \"Sarah Chen\",\r\n    role: \"Product Designer @ Stripe\",\r\n    content: \"This library has completely transformed how we build internal tools. The attention to detail is unmatched.\",\r\n    avatar: \"https://api.dicebear.com/7.x/avataaars/svg?seed=Sarah\",\r\n  },\r\n  {\r\n    name: \"Alex Rivera\",\r\n    role: \"CTO @ Vercel\",\r\n    content: \"Ideally, every project would start with this foundation. It's clean, performant, and absolutely stunning.\",\r\n    avatar: \"https://api.dicebear.com/7.x/avataaars/svg?seed=Alex\",\r\n  },\r\n  {\r\n    name: \"Jordan Lee\",\r\n    role: \"Frontend Lead @ Airbnb\",\r\n    content: \"The animations are buttery smooth and the code is a joy to work with. Highly recommended.\",\r\n    avatar: \"https://api.dicebear.com/7.x/avataaars/svg?seed=Jordan\",\r\n  },\r\n  {\r\n    name: \"Emily Zhang\",\r\n    role: \"Developer Advocate\",\r\n    content: \"I've never seen a component library this polished right out of the box. True craftsmanship.\",\r\n    avatar: \"https://api.dicebear.com/7.x/avataaars/svg?seed=Emily\",\r\n  },\r\n  {\r\n    name: \"David Kim\",\r\n    role: \"Indie Hacker\",\r\n    content: \"Shipped my SaaS in record time thanks to these blocks. The bento grids are a game changer.\",\r\n    avatar: \"https://api.dicebear.com/7.x/avataaars/svg?seed=David\",\r\n  },\r\n];\r\n\r\nconst MarqueeCard = ({ testimonial }: { testimonial: typeof testimonials[0] }) => (\r\n  <div className=\"relative w-[350px] flex-shrink-0 rounded-2xl border border-border/60 bg-card p-6 shadow-sm mx-3\">\r\n    <Quote className=\"absolute top-6 right-6 h-4 w-4 text-muted-foreground/20\" />\r\n    <div className=\"flex flex-col gap-4\">\r\n      <div className=\"flex gap-1\">\r\n        {[...Array(5)].map((_, i) => (\r\n          <Star key={i} className=\"h-4 w-4 fill-amber-500 text-amber-500\" />\r\n        ))}\r\n      </div>\r\n      <p className=\"text-muted-foreground leading-relaxed\">\r\n        \"{testimonial.content}\"\r\n      </p>\r\n      <div className=\"flex items-center gap-3 mt-2\">\r\n        <div className=\"h-10 w-10 overflow-hidden rounded-full border border-border bg-muted\">\r\n          <img src={testimonial.avatar} alt={testimonial.name} className=\"h-full w-full object-cover\" />\r\n        </div>\r\n        <div>\r\n          <h4 className=\"font-semibold text-sm\">{testimonial.name}</h4>\r\n          <p className=\"text-xs text-muted-foreground\">{testimonial.role}</p>\r\n        </div>\r\n      </div>\r\n    </div>\r\n  </div>\r\n);\r\n\r\nexport function TestimonialsMarquee() {\r\n  return (\r\n    <section className=\"py-24 bg-background overflow-hidden relative\">\r\n      <div className=\"max-w-7xl mx-auto px-4 md:px-8 mb-16 text-center\">\r\n        <h2 className=\"text-4xl font-black tracking-tight mb-4\">Loved by <span className=\"text-primary\">Builders</span></h2>\r\n        <p className=\"text-lg text-muted-foreground max-w-2xl mx-auto\">\r\n          Join thousands of developers building the future of the web.\r\n        </p>\r\n      </div>\r\n\r\n      <div className=\"flex flex-col gap-6 mask-linear-fade\">\r\n        {/* Row 1: Left to Right */}\r\n        <div className=\"flex overflow-hidden\">\r\n          <motion.div\r\n            animate={{ x: [0, -1000] }}\r\n            transition={{ duration: 40, repeat: Infinity, ease: \"linear\" }}\r\n            className=\"flex\"\r\n          >\r\n            {[...testimonials, ...testimonials, ...testimonials].map((t, i) => (\r\n              <MarqueeCard key={`row1-${i}`} testimonial={t} />\r\n            ))}\r\n          </motion.div>\r\n        </div>\r\n\r\n        {/* Row 2: Right to Left */}\r\n        <div className=\"flex overflow-hidden\">\r\n          <motion.div\r\n            animate={{ x: [-1000, 0] }}\r\n            transition={{ duration: 40, repeat: Infinity, ease: \"linear\" }}\r\n            className=\"flex\"\r\n          >\r\n            {[...testimonials, ...testimonials, ...testimonials].map((t, i) => (\r\n              <MarqueeCard key={`row2-${i}`} testimonial={t} />\r\n            ))}\r\n          </motion.div>\r\n        </div>\r\n      </div>\r\n\r\n      {/* Fade Edges */}\r\n      <div className=\"absolute inset-y-0 left-0 w-24 bg-gradient-to-r from-background to-transparent z-10 pointer-events-none\" />\r\n      <div className=\"absolute inset-y-0 right-0 w-24 bg-gradient-to-l from-background to-transparent z-10 pointer-events-none\" />\r\n    </section>\r\n  );\r\n}\r\n\r\nexport default TestimonialsMarquee;\r\n",
            "type": "registry:block"
        }
    ],
    "category": "testimonials"
}